{
  "name": "Byzantine Cistern Economy",
  "civilization": ["Byzantines", "Macedonian Dynasty"],
  "author": "RTSLytics",
  "source": "https://rtslytics.app/builds/byzantines-cistern-eco",
  "build_order": [
    {
      "population_count": -1,
      "villager_count": 6,
      "age": 1,
      "resources": { "food": 5, "wood": 0, "gold": 0, "stone": 1 },
      "notes": [
        "Send 5 starting villagers to sheep and 1 to stone. Byzantines need early stone for Cisterns, so do not skip this.",
        "Scout for sheep, gold, and your opponent."
      ],
      "time": "0:30"
    },
    {
      "population_count": -1,
      "villager_count": 9,
      "age": 1,
      "resources": { "food": 5, "wood": 2, "gold": 0, "stone": 2 },
      "notes": [
        "Put new villagers onto wood, but keep 2 on stone until your first 50 stone is banked.",
        "Build a House, then plan a tight base layout so the first Cistern boosts the Town Center and drop-offs."
      ],
      "time": "1:30"
    },
    {
      "population_count": -1,
      "villager_count": 12,
      "age": 1,
      "resources": { "food": 7, "wood": 3, "gold": 0, "stone": 2 },
      "notes": [
        "Keep most villagers on food and add a Mill on berries.",
        "The stone villagers are paying for your Cistern network; move them only after the first Cistern is affordable."
      ],
      "time": "2:45"
    },
    {
      "population_count": -1,
      "villager_count": 15,
      "age": 1,
      "resources": { "food": 8, "wood": 2, "gold": 3, "stone": 2 },
      "notes": [
        "Send 3 villagers to gold with a Mining Camp.",
        "With about 400 food and 200 wood, age up to Feudal. Keep the stone line running for the first Cistern."
      ],
      "time": "4:30"
    },
    {
      "population_count": -1,
      "villager_count": 18,
      "age": 1,
      "resources": { "food": 8, "wood": 3, "gold": 5, "stone": 2 },
      "notes": [
        "Keep gathering through the age-up and make sure 50 stone is ready for your first Cistern.",
        "Decide which matchup weakness a mercenary contract should cover once you hit Feudal."
      ],
      "time": "5:30"
    },
    {
      "population_count": -1,
      "villager_count": 21,
      "age": 2,
      "resources": { "food": 9, "wood": 4, "gold": 6, "stone": 2 },
      "notes": [
        "In Feudal, build the first Cistern in the middle of your base to boost the economy around it.",
        "Make Limitanei (tanky spearmen) to hold ground cheaply while you scale."
      ],
      "time": "6:30"
    },
    {
      "population_count": -1,
      "villager_count": 25,
      "age": 2,
      "resources": { "food": 11, "wood": 4, "gold": 8, "stone": 2 },
      "notes": [
        "Use a Mercenary contract to hire units that patch your weakest matchup spot.",
        "Keep 1 to 2 villagers on stone if you want a second Cistern soon; otherwise move them to food or gold."
      ],
      "time": "8:00"
    },
    {
      "population_count": -1,
      "villager_count": 29,
      "age": 2,
      "resources": { "food": 12, "wood": 5, "gold": 10, "stone": 2 },
      "notes": [
        "Add stone again before expanding the Cistern network; broken or missing Cisterns slow the whole civ.",
        "Bank toward Castle Age for your power units."
      ],
      "time": "9:30"
    },
    {
      "population_count": -1,
      "villager_count": 33,
      "age": 3,
      "resources": { "food": 12, "wood": 5, "gold": 13, "stone": 3 },
      "notes": [
        "In Castle Age, add Cataphracts backed by mercenaries and siege.",
        "Convert your economic lead into map control with Cataphract pushes, and keep the Cistern network alive."
      ],
      "time": "11:30"
    }
  ]
}
