{
  "name": "Jeanne d'Arc Aggression (Valdemar)",
  "civilization": "Jeanne d'Arc",
  "author": "Valdemar1902",
  "source": "https://aoe4guides.com/builds/ss0UMX3M9DRmkcPLRvk5",
  "archetype": "Feudal aggression",
  "difficulty": "easy",
  "reasoning": "Valdemar's JD plan and the top-rated Jeanne build: level Jeanne on early skirmishes, then snowball with Royal Knights once she hits her champion levels. Her XP makes passivity a waste — this build keeps her fighting.",
  "build_order": [
    {
      "population_count": -1,
      "villager_count": 6,
      "age": 1,
      "resources": {
        "food": 6,
        "wood": 0,
        "gold": 0,
        "stone": 0
      },
      "notes": [
        "Jeanne darc peasant 1 stays on sheep the whole Dark Age",
        "Start 6 on sheep and look for the 1st deer pack around your base (there are two, one will be immediately outside tc vision range)"
      ],
      "time": "0:00"
    },
    {
      "population_count": -1,
      "villager_count": 7,
      "age": 1,
      "resources": {
        "food": 2,
        "wood": 5,
        "gold": 0,
        "stone": 0
      },
      "notes": [
        "Once deer is found, take 5 villager and gather 50 wood and house"
      ],
      "time": "0:35"
    },
    {
      "population_count": -1,
      "villager_count": 8,
      "age": 1,
      "resources": {
        "food": 3,
        "wood": 0,
        "gold": 0,
        "stone": 0,
        "builder": 5
      },
      "notes": [
        "Build a mill on deer . Research survival techniques -> wheelbarrow immediately"
      ],
      "time": "0:50"
    },
    {
      "population_count": -1,
      "villager_count": 10,
      "age": 1,
      "resources": {
        "food": 6,
        "wood": 0,
        "gold": 4,
        "stone": 0
      },
      "notes": [
        "Pull 4 villager from sheep to gold when mill is finished"
      ],
      "time": "1:20"
    },
    {
      "population_count": -1,
      "villager_count": 0,
      "age": 1,
      "resources": {
        "food": 0,
        "wood": 0,
        "gold": 0,
        "stone": 0
      },
      "notes": [
        "Rally point food until age 2"
      ]
    },
    {
      "population_count": -1,
      "villager_count": 15,
      "age": 1,
      "resources": {
        "food": 7,
        "wood": 0,
        "gold": 4,
        "stone": 0,
        "builder": 4
      },
      "notes": [
        "Jeanne darc peasant 1 + 3 sheep villager build school of cavalry"
      ],
      "time": "3:13"
    },
    {
      "population_count": -1,
      "villager_count": 15,
      "age": 1,
      "resources": {
        "food": 5,
        "wood": 2,
        "gold": 4,
        "stone": 0,
        "builder": 4
      },
      "notes": [
        "Take rest of sheep villager and go to wood."
      ],
      "time": "3:13"
    },
    {
      "population_count": -1,
      "villager_count": 16,
      "age": 1,
      "resources": {
        "food": 5,
        "wood": 3,
        "gold": 4,
        "stone": 0,
        "builder": 4
      },
      "notes": [
        "Rally point wood until 8"
      ],
      "time": "3:20"
    },
    {
      "population_count": -1,
      "villager_count": 15,
      "age": 2,
      "resources": {
        "food": 5,
        "wood": 6,
        "gold": 4,
        "stone": 0
      },
      "notes": [
        "Queue specialized pick and royal knight 2 upon reaching feudal"
      ],
      "time": "4:37"
    },
    {
      "population_count": -1,
      "villager_count": 0,
      "age": 2,
      "resources": {
        "food": 0,
        "wood": 0,
        "gold": 0,
        "stone": 0
      },
      "notes": [
        "Once 8 on wood rally then to gold until 8 and then back to food"
      ]
    },
    {
      "population_count": -1,
      "villager_count": 21,
      "age": 2,
      "resources": {
        "food": 8,
        "wood": 8,
        "gold": 5,
        "stone": 0
      },
      "notes": [
        "2nd stable"
      ],
      "time": "5:36"
    },
    {
      "population_count": -1,
      "villager_count": 25,
      "age": 2,
      "resources": {
        "food": 9,
        "wood": 8,
        "gold": 8,
        "stone": 0
      },
      "notes": [
        "Archery range & outpost if needed on gold and deer"
      ],
      "time": "6:30"
    }
  ]
}
