{
  "name": "Mongols Fast Castle Age",
  "civilization": ["Mongols", "Golden Horde"],
  "author": "RTSLytics",
  "source": "https://rtslytics.app/builds/mongols-fast-castle",
  "build_order": [
    {
      "population_count": -1,
      "villager_count": 6,
      "age": 1,
      "resources": {
        "food": 6,
        "wood": 0,
        "gold": 0,
        "stone": 0
      },
      "notes": [
        "Send all 6 villagers to sheep. Mongols have no Houses, so you never get housed.",
        "Use your two Scouts to find sheep and herd them to the Town Center."
      ],
      "time": "0:30"
    },
    {
      "population_count": -1,
      "villager_count": 9,
      "age": 1,
      "resources": {
        "food": 6,
        "wood": 3,
        "gold": 0,
        "stone": 0
      },
      "notes": [
        "Put the next 3 villagers on wood and build a Lumber Camp.",
        "Consider using the Ovoo on a stone outcrop to gather extra stone for free."
      ],
      "time": "1:30"
    },
    {
      "population_count": -1,
      "villager_count": 12,
      "age": 1,
      "resources": {
        "food": 8,
        "wood": 4,
        "gold": 0,
        "stone": 0
      },
      "notes": [
        "Keep adding villagers to food to reach the Feudal Age quickly.",
        "Build a Mill on berries when your sheep are running low."
      ],
      "time": "2:45"
    },
    {
      "population_count": -1,
      "villager_count": 14,
      "age": 1,
      "resources": {
        "food": 8,
        "wood": 6,
        "gold": 0,
        "stone": 0
      },
      "notes": [
        "Add villagers to wood. You will need wood for both age-up landmarks.",
        "With about 400 food and 200 wood, age up to the Feudal Age."
      ],
      "time": "4:00"
    },
    {
      "population_count": -1,
      "villager_count": 16,
      "age": 1,
      "resources": {
        "food": 6,
        "wood": 7,
        "gold": 3,
        "stone": 0
      },
      "notes": [
        "Send 3 villagers to gold and build a Mining Camp.",
        "Pick a cheap Feudal landmark and keep gathering during the age-up."
      ],
      "time": "5:00"
    },
    {
      "population_count": -1,
      "villager_count": 18,
      "age": 2,
      "resources": {
        "food": 8,
        "wood": 6,
        "gold": 4,
        "stone": 0
      },
      "notes": [
        "In Feudal Age, do not stop villager production. Aim straight for the Castle Age.",
        "Move some villagers from wood to gold to afford the Castle age-up cost."
      ],
      "time": "6:00"
    },
    {
      "population_count": -1,
      "villager_count": 21,
      "age": 2,
      "resources": {
        "food": 9,
        "wood": 5,
        "gold": 7,
        "stone": 0
      },
      "notes": [
        "Balance your villagers across food, wood, and gold for a smooth age-up.",
        "Trade with the Silver Tree or use Ovoo bonuses to speed up your economy."
      ],
      "time": "7:30"
    },
    {
      "population_count": -1,
      "villager_count": 24,
      "age": 2,
      "resources": {
        "food": 9,
        "wood": 4,
        "gold": 11,
        "stone": 0
      },
      "notes": [
        "Once you have about 1200 food and 1200 gold, click up to the Castle Age.",
        "Choose a landmark like the Kurultai for a strong army aura or the Steppe Redoubt for defense."
      ],
      "time": "8:45"
    },
    {
      "population_count": -1,
      "villager_count": 26,
      "age": 3,
      "resources": {
        "food": 10,
        "wood": 5,
        "gold": 11,
        "stone": 0
      },
      "notes": [
        "When you reach Castle Age, build a military building such as an Archery Range or Stable.",
        "Mangudai are an excellent mobile Castle Age unit to harass and raid."
      ],
      "time": "10:15"
    },
    {
      "population_count": -1,
      "villager_count": 30,
      "age": 3,
      "resources": {
        "food": 12,
        "wood": 6,
        "gold": 12,
        "stone": 0
      },
      "notes": [
        "Research blacksmith and economy upgrades to strengthen your army and economy.",
        "Use the mobility of Mongol units to control the map and pressure your opponent."
      ],
      "time": "12:00"
    }
  ]
}
